CHANGES.rst
Makefile
README.rst
ez_setup.py
setup.cfg
setup.py
Otto.egg-info/PKG-INFO
Otto.egg-info/SOURCES.txt
Otto.egg-info/dependency_links.txt
Otto.egg-info/not-zip-safe
Otto.egg-info/requires.txt
Otto.egg-info/top_level.txt
otto/__init__.py
otto/app.py
otto/publisher.py
otto/router.py
otto/utils.py
otto/docs/conf.py
otto/docs/faq.rst
otto/docs/getting_started.rst
otto/docs/glossary.rst
otto/docs/index.rst
otto/docs/mapping.rst
otto/docs/readme.rst
otto/docs/reference.rst
otto/docs/security.rst
otto/tests/__init__.py
otto/tests/test_app.py
otto/tests/test_dispatcher.py
otto/tests/test_doctests.py
otto/tests/test_router.py
otto/tests/utils.py
otto/tests/mock/__init__.py
otto/tests/mock/simple_server.py
site/index.html
site/main.css
site/otto.png