Metadata-Version: 1.0
Name: Otto
Version: 1.2
Summary: WSGI-compliant HTTP publisher.
Home-page: http://www.ottohttp.org
Author: Malthe Borch
Author-email: mborch@gmail.com
License: BSD
Keywords: wsgi publisher router
Platform: UNKNOWN
Classifier: Development Status :: 3 - Alpha
Classifier: Intended Audience :: Developers
Classifier: Programming Language :: Python
